Metadata-Version: 1.1
Name: remotedroid
Version: 0.0.1.dev0
Summary: Webapp to remotely control Android devices via adb
Home-page: https://github.com/storborg/remotedroid
Author: Scott Torborg
Author-email: storborg@gmail.com
License: MIT
Keywords: android adb vnc remote viewer
Platform: UNKNOWN
Classifier: Development Status :: 2 - Pre-Alpha
Classifier: License :: OSI Approved :: MIT License
